coalesce/__init__.py
coalesce-0.3.dist-info/DESCRIPTION.rst
coalesce-0.3.dist-info/METADATA
coalesce-0.3.dist-info/RECORD
coalesce-0.3.dist-info/WHEEL
coalesce-0.3.dist-info/metadata.json
coalesce-0.3.dist-info/top_level.txt
